featrixclient/__init__.py
featrixclient/api.py
featrixclient/api_urls.py
featrixclient/config.py
featrixclient/featrix_embedding_space.py
featrixclient/featrix_job.py
featrixclient/featrix_neural_function.py
featrixclient/featrix_predictions.py
featrixclient/featrix_project.py
featrixclient/featrix_upload.py
featrixclient/networkclient.py
featrixclient/signaling.py
featrixclient/utils.py
featrixclient/version.py
featrixclient/exceptions/__init__.py
featrixclient/models/__init__.py
featrixclient/models/activity.py
featrixclient/models/api_key.py
featrixclient/models/association.py
featrixclient/models/embedding_space.py
featrixclient/models/featrix_base.py
featrixclient/models/feed.py
featrixclient/models/fmodel.py
featrixclient/models/invitation.py
featrixclient/models/job_dispatching.py
featrixclient/models/job_meta.py
featrixclient/models/job_requests.py
featrixclient/models/job_type.py
featrixclient/models/job_usage.py
featrixclient/models/model.py
featrixclient/models/organization.py
featrixclient/models/prediction.py
featrixclient/models/project.py
featrixclient/models/pydantic_objectid.py
featrixclient/models/training.py
featrixclient/models/upload.py
featrixclient/models/user.py
featrixclient-2024.1024.1.dist-info/LICENSE
featrixclient-2024.1024.1.dist-info/METADATA
featrixclient-2024.1024.1.dist-info/WHEEL
featrixclient-2024.1024.1.dist-info/top_level.txt
featrixclient-2024.1024.1.dist-info/RECORD
