Metadata-Version: 2.1
Name: featrixclient
Version: 2024.1024.1
Summary: Featrix AI API
Home-page: https://featrix.com
Download-URL: https://github.com/Featrix/opensource.git
Author: Featrix, Inc.
Author-email: hello@featrix.ai
License: MIT License
Keywords: ML,AI,embedding,embeddings,tabular,embeddings,vectorize,automl,xgboost,neuralnetwork,eda
Classifier: Development Status :: 4 - Beta
Classifier: Environment :: Console
Classifier: Intended Audience :: Developers
Classifier: Intended Audience :: Information Technology
Classifier: Intended Audience :: Science/Research
Classifier: License :: OSI Approved :: MIT License
Classifier: Natural Language :: English
Classifier: Operating System :: POSIX :: Linux
Classifier: Programming Language :: Python :: 3
Classifier: Programming Language :: Python :: 3.11
Classifier: Topic :: System :: Installation/Setup
Classifier: Topic :: Utilities
Requires-Python: >=3.10
License-File: LICENSE
Requires-Dist: pydantic[email] (>=2.5.0)
Requires-Dist: pydantic-core (>=2.14.5)
Requires-Dist: pydantic-settings (>=2.4.0)
Requires-Dist: bson
Requires-Dist: fastapi (>=0.106.0)
Requires-Dist: pandas (>=2.1.4)
Requires-Dist: psutil (>=5.9.5)
Requires-Dist: requests (>=2.31.0)
Requires-Dist: eval-type-backport ; python_version < "3.10"
